askvideos/__init__.py
askvideos/client.py
askvideos/examples/movie.py
askvideos/examples/movie2.py
askvideos-0.2.2.dist-info/METADATA
askvideos-0.2.2.dist-info/WHEEL
askvideos-0.2.2.dist-info/top_level.txt
askvideos-0.2.2.dist-info/RECORD
