Metadata-Version: 2.1
Name: askvideos
Version: 0.2.2
Summary: AskVideos python library
Home-page: https://github.com/AskYoutubeAI/askvideos-py
Author: AskVideos
Author-email: askutubeai@gmail.com
Requires-Python: >=3.6
Requires-Dist: requests
